jsonfeed/__init__.py
tests/__init__.py
tests/test_feed.py
tests/test_import.py
tests/test_item.py
jsonfeed_util-1.2.0.dist-info/METADATA
jsonfeed_util-1.2.0.dist-info/WHEEL
jsonfeed_util-1.2.0.dist-info/top_level.txt
jsonfeed_util-1.2.0.dist-info/RECORD
