Metadata-Version: 2.2
Name: jsonfeed-util
Version: 1.2.0
Summary: Python package for parsing and generating JSON feeds.
Home-page: https://github.com/lukasschwab/jsonfeed
Author: Lukas Schwab
Author-email: lukas.schwab@gmail.com
License: MIT
Keywords: json feed jsonfeed
Classifier: Programming Language :: Python
Classifier: Programming Language :: Python :: 3
Classifier: Programming Language :: Python :: 3.9
Classifier: Programming Language :: Python :: 3.10
Classifier: Programming Language :: Python :: 3.11
Classifier: Programming Language :: Python :: 3.12
Classifier: Programming Language :: Python :: 3.13
Classifier: License :: OSI Approved :: MIT License
Classifier: Operating System :: OS Independent
Dynamic: author
Dynamic: author-email
Dynamic: classifier
Dynamic: description
Dynamic: description-content-type
Dynamic: home-page
Dynamic: keywords
Dynamic: license
Dynamic: summary
